designer/__init__.py
designer/info.py
designer/pydesigner.py
designer/fitting/__init__.py
designer/fitting/dirs10000.csv
designer/fitting/dirs256.csv
designer/fitting/dirs30.csv
designer/fitting/dwi_fnames.py
designer/fitting/dwidirs.py
designer/fitting/dwipy.py
designer/fitting/spherical_grid.csv
designer/fitting/thresholds.py
designer/plotting/__init__.py
designer/plotting/motionplot.py
designer/plotting/outlierplot.py
designer/plotting/snrplot.py
designer/postprocessing/__init__.py
designer/postprocessing/filters.py
designer/preprocessing/__init__.py
designer/preprocessing/mrinfoutil.py
designer/preprocessing/mrpreproc.py
designer/preprocessing/preparation.py
designer/preprocessing/rician.py
designer/preprocessing/smoothing.py
designer/preprocessing/util.py
designer/system/__init__.py
designer/system/utils.py
designer/tractography/__init__.py
designer/tractography/dsistudio.py
designer/tractography/odf.py
designer/tractography/sphericalsampling.py
PyDesigner_DWI-1.0.1.dist-info/LICENSE
PyDesigner_DWI-1.0.1.dist-info/METADATA
PyDesigner_DWI-1.0.1.dist-info/WHEEL
PyDesigner_DWI-1.0.1.dist-info/entry_points.txt
PyDesigner_DWI-1.0.1.dist-info/top_level.txt
PyDesigner_DWI-1.0.1.dist-info/RECORD
