Metadata-Version: 2.1
Name: PyDesigner-DWI
Version: 1.0.1
Summary: Python Port of NYU's Designer pipeline for dMRI processing
Home-page: https://github.com/m-ama/PyDesigner
Author: PyDesigner developers
Author-email: bridge@musc.edu
Maintainer: Siddhartha Dhiman
License: CUSTOM
Classifier: Programming Language :: Python :: 3.7
Classifier: License :: OSI Approved :: Mozilla Public License 2.0 (MPL 2.0)
Classifier: Operating System :: OS Independent
Classifier: Topic :: Scientific/Engineering :: Bio-Informatics
Classifier: Topic :: Scientific/Engineering :: Information Analysis
Classifier: Topic :: Scientific/Engineering :: Mathematics
Classifier: Topic :: Scientific/Engineering :: Physics
Requires-Python: >=3.6
License-File: LICENSE
Requires-Dist: numpy >=1.19
Requires-Dist: scipy >=1.5
Requires-Dist: matplotlib >=3.3
Requires-Dist: joblib >=0.16
Requires-Dist: tqdm >=4.40
Requires-Dist: multiprocess >=0.70
Requires-Dist: nibabel >=3.2
Requires-Dist: dipy >=1.2
Requires-Dist: cvxpy >=1.1
